api.py
main.py
rag_utils.py
schemas.py
settings.py
utils.py
routers/frontend_router.py
routers/rag_router.py
routers/text_router.py
templates/chat.html
templates/graph_viewer.html
templates/home.html
templates/rag-chat.html
lightrag_exploration-0.1.1.dist-info/METADATA
lightrag_exploration-0.1.1.dist-info/WHEEL
lightrag_exploration-0.1.1.dist-info/entry_points.txt
lightrag_exploration-0.1.1.dist-info/top_level.txt
lightrag_exploration-0.1.1.dist-info/RECORD
