Metadata-Version: 2.4
Name: lightrag-exploration
Version: 0.1.1
Summary: A lightweight RAG exploration tool.
Author: James Twose
Requires-Python: >=3.9
Requires-Dist: fastapi
Requires-Dist: uvicorn[standard]
Requires-Dist: jinja2
Requires-Dist: httpx
Requires-Dist: python-multipart
Requires-Dist: pydantic-settings
Requires-Dist: lightrag-hku
